easy_excel_util/__init__.py
easy_excel_util/base_field.py
easy_excel_util/builder.py
easy_excel_util/utils.py
easy_excel_util/export_pack/__init__.py
easy_excel_util/export_pack/export_cell.py
easy_excel_util/export_pack/export_field.py
easy_excel_util/export_pack/export_middleware.py
easy_excel_util/export_pack/export_row.py
easy_excel_util/export_pack/export_sheet.py
easy_excel_util/export_pack/export_workbook.py
easy_excel_util/export_pack/sheet_map.py
easy_excel_util/export_pack/factory/__init__.py
easy_excel_util/export_pack/factory/base.py
easy_excel_util/export_pack/factory/xls.py
easy_excel_util/export_pack/factory/xlsx.py
easy_excel_util/import_pack/__init__.py
easy_excel_util/import_pack/import_cell.py
easy_excel_util/import_pack/import_field.py
easy_excel_util/import_pack/import_row.py
easy_excel_util/import_pack/import_sheet.py
easy_excel_util/import_pack/import_workbook.py
easy_excel_util/import_pack/reader_data.py
easy_excel_util/import_pack/result.py
easy_excel_util/import_pack/factory/__init__.py
easy_excel_util/import_pack/factory/base.py
easy_excel_util/import_pack/factory/xls.py
easy_excel_util/import_pack/factory/xlsx.py
easy_excel_util-2.1.1.dist-info/LICENSE
easy_excel_util-2.1.1.dist-info/METADATA
easy_excel_util-2.1.1.dist-info/WHEEL
easy_excel_util-2.1.1.dist-info/top_level.txt
easy_excel_util-2.1.1.dist-info/RECORD
