Metadata-Version: 2.1
Name: easy-excel-util
Version: 2.1.1
Summary: a package to easy import or export excel | excel操作简化，包含导入和导出功能
Home-page: https://github.com/ChaoqiYin/easy-excel.git
Author: ChaoqiYin
Author-email: 305111632@qq.com
License: MIT
Platform: UNKNOWN
Classifier: License :: OSI Approved :: MIT License
Classifier: Programming Language :: Python
Classifier: Programming Language :: Python :: 3
Classifier: Programming Language :: Python :: 3.6
Classifier: Programming Language :: Python :: Implementation :: CPython
Classifier: Programming Language :: Python :: Implementation :: PyPy
Requires-Python: >=3.6.0
License-File: LICENSE
Requires-Dist: xlrd (>=1.2)
Requires-Dist: xlwt (>=1.3)
Requires-Dist: openpyxl (>=3.0.5)
